tsuyo_quicksample.py
tsuyo_quicksample-0.0.1.dist-info/LICENSE
tsuyo_quicksample-0.0.1.dist-info/METADATA
tsuyo_quicksample-0.0.1.dist-info/WHEEL
tsuyo_quicksample-0.0.1.dist-info/top_level.txt
tsuyo_quicksample-0.0.1.dist-info/RECORD
