Metadata-Version: 2.1
Name: tsuyo_quicksample
Version: 0.0.1
Summary: Quicksample Test Package
Author: Tsuyoshi Miyake
License: UNKNOWN
Platform: UNKNOWN
Classifier: Programming Language :: Python :: 3
Classifier: License :: OSI Approved :: MIT License
Classifier: Operating System :: OS Independent
Requires-Python: >=3.6
License-File: LICENSE
